mpl_ascii/__init__.py
mpl_ascii/artists/Annotation.py
mpl_ascii/artists/Legend.py
mpl_ascii/artists/Line2D.py
mpl_ascii/artists/LineCollection.py
mpl_ascii/artists/PathCollection.py
mpl_ascii/artists/PolyCollection.py
mpl_ascii/artists/Polygon.py
mpl_ascii/artists/QuadContourSet.py
mpl_ascii/artists/Rectangle.py
mpl_ascii/artists/Spine.py
mpl_ascii/artists/Text.py
mpl_ascii/artists/XAxis.py
mpl_ascii/artists/YAxis.py
mpl_ascii/artists/__init__.py
mpl_ascii/artists/transform_helpers.py
mpl_ascii/artists/types.py
mpl_ascii/layout/__init__.py
mpl_ascii/layout/constants.py
mpl_ascii/layout/discrete_point.py
mpl_ascii/layout/layout_shape.py
mpl_ascii/layout/layout_text.py
mpl_ascii/layout/rasterize.py
mpl_ascii/layout/render_plan.py
mpl_ascii/layout/transforms.py
mpl_ascii/parsing/__init__.py
mpl_ascii/parsing/figure.py
mpl_ascii/parsing/shape.py
mpl_ascii/parsing/transform.py
mpl_ascii/presentation/__init__.py
mpl_ascii/presentation/color_policy.py
mpl_ascii/presentation/glyphs.py
mpl_ascii/presentation/visibility.py
mpl_ascii/rendering/__init__.py
mpl_ascii/rendering/canvas.py
mpl_ascii/rendering/canvas_manager.py
mpl_ascii/rendering/render.py
mpl_ascii/scene/__init__.py
mpl_ascii/scene/entities.py
mpl_ascii/scene/fingerprint.py
mpl_ascii/scene/store.py
mpl_ascii/scene/geometry/__init__.py
mpl_ascii/scene/geometry/affine.py
mpl_ascii/scene/geometry/matrix.py
mpl_ascii/scene/geometry/point.py
mpl_ascii-1.0.1.dist-info/licenses/LICENSE
mpl_ascii-1.0.1.dist-info/METADATA
mpl_ascii-1.0.1.dist-info/WHEEL
mpl_ascii-1.0.1.dist-info/top_level.txt
mpl_ascii-1.0.1.dist-info/RECORD
