Metadata-Version: 2.4
Name: mpl_ascii
Version: 1.0.1
Summary: A matplotlib backend that produces plots using only ASCII characters
Author: Chris Cave
Maintainer: Chris Cave
License: MIT License
Project-URL: Homepage, https://github.com/chriscave/mpl_ascii
Keywords: matplotlib,plotting,ASCII
Requires-Python: >=3.7
License-File: LICENSE
Requires-Dist: matplotlib>=3.5.3
Requires-Dist: rich>=13.7.1
Dynamic: license-file
